amazon_dsp_sdk/__init__.py
amazon_dsp_sdk/_client.py
amazon_dsp_sdk/_configuration.py
amazon_dsp_sdk/_patch.py
amazon_dsp_sdk/_serialization.py
amazon_dsp_sdk/_vendor.py
amazon_dsp_sdk/py.typed
amazon_dsp_sdk/_operations/__init__.py
amazon_dsp_sdk/_operations/_operations.py
amazon_dsp_sdk/_operations/_patch.py
amazon_dsp_sdk/aio/__init__.py
amazon_dsp_sdk/aio/_client.py
amazon_dsp_sdk/aio/_configuration.py
amazon_dsp_sdk/aio/_patch.py
amazon_dsp_sdk/aio/_vendor.py
amazon_dsp_sdk/aio/_operations/__init__.py
amazon_dsp_sdk/aio/_operations/_operations.py
amazon_dsp_sdk/aio/_operations/_patch.py
amazon_dsp_sdk-0.1.0.dist-info/METADATA
amazon_dsp_sdk-0.1.0.dist-info/WHEEL
amazon_dsp_sdk-0.1.0.dist-info/entry_points.txt
amazon_dsp_sdk-0.1.0.dist-info/top_level.txt
amazon_dsp_sdk-0.1.0.dist-info/RECORD
