Metadata-Version: 2.1
Name: amazon-dsp-sdk
Version: 0.1.0
Summary: A Python SDK for Amazon DSP API
Home-page: https://github.com/yourusername/your_sdk_repo
Author: Thota Mohan Reddy
Author-email: thotamohanreddy993@gmail.com
Classifier: Programming Language :: Python :: 3
Classifier: License :: OSI Approved :: MIT License
Classifier: Operating System :: OS Independent
Requires-Python: >=3.6
Requires-Dist: requests
Requires-Dist: azure-core
